<annotation>
	<folder>祝远</folder>
	<filename>IMG_20210122_175626.jpg</filename>
	<path>C:\Users\86156\Desktop\data\祝远\IMG_20210122_175626.jpg</path>
	<source>
		<database>Unknown</database>
	</source>
	<size>
		<width>4000</width>
		<height>3000</height>
		<depth>3</depth>
	</size>
	<segmented>0</segmented>
	<object>
		<name>1</name>
		<pose>Unspecified</pose>
		<truncated>0</truncated>
		<difficult>0</difficult>
		<bndbox>
			<xmin>940</xmin>
			<ymin>1047</ymin>
			<xmax>1108</xmax>
			<ymax>1757</ymax>
		</bndbox>
	</object>
	<object>
		<name>.</name>
		<pose>Unspecified</pose>
		<truncated>0</truncated>
		<difficult>0</difficult>
		<bndbox>
			<xmin>1095</xmin>
			<ymin>1054</ymin>
			<xmax>1227</xmax>
			<ymax>1770</ymax>
		</bndbox>
	</object>
	<object>
		<name>8</name>
		<pose>Unspecified</pose>
		<truncated>0</truncated>
		<difficult>0</difficult>
		<bndbox>
			<xmin>1240</xmin>
			<ymin>1035</ymin>
			<xmax>1698</xmax>
			<ymax>1751</ymax>
		</bndbox>
	</object>
	<object>
		<name>.</name>
		<pose>Unspecified</pose>
		<truncated>0</truncated>
		<difficult>0</difficult>
		<bndbox>
			<xmin>1711</xmin>
			<ymin>1102</ymin>
			<xmax>1862</xmax>
			<ymax>1370</ymax>
		</bndbox>
	</object>
	<object>
		<name>.</name>
		<pose>Unspecified</pose>
		<truncated>0</truncated>
		<difficult>0</difficult>
		<bndbox>
			<xmin>1685</xmin>
			<ymin>1393</ymin>
			<xmax>1830</xmax>
			<ymax>1589</ymax>
		</bndbox>
	</object>
	<object>
		<name>.</name>
		<pose>Unspecified</pose>
		<truncated>0</truncated>
		<difficult>0</difficult>
		<bndbox>
			<xmin>1666</xmin>
			<ymin>1609</ymin>
			<xmax>1808</xmax>
			<ymax>1793</ymax>
		</bndbox>
	</object>
	<object>
		<name>8</name>
		<pose>Unspecified</pose>
		<truncated>0</truncated>
		<difficult>0</difficult>
		<bndbox>
			<xmin>1830</xmin>
			<ymin>1054</ymin>
			<xmax>2288</xmax>
			<ymax>1799</ymax>
		</bndbox>
	</object>
	<object>
		<name>.</name>
		<pose>Unspecified</pose>
		<truncated>0</truncated>
		<difficult>0</difficult>
		<bndbox>
			<xmin>2253</xmin>
			<ymin>1102</ymin>
			<xmax>2443</xmax>
			<ymax>1418</ymax>
		</bndbox>
	</object>
	<object>
		<name>.</name>
		<pose>Unspecified</pose>
		<truncated>0</truncated>
		<difficult>0</difficult>
		<bndbox>
			<xmin>2243</xmin>
			<ymin>1418</ymin>
			<xmax>2417</xmax>
			<ymax>1618</ymax>
		</bndbox>
	</object>
	<object>
		<name>.</name>
		<pose>Unspecified</pose>
		<truncated>0</truncated>
		<difficult>0</difficult>
		<bndbox>
			<xmin>2227</xmin>
			<ymin>1618</ymin>
			<xmax>2424</xmax>
			<ymax>1844</ymax>
		</bndbox>
	</object>
	<object>
		<name>8</name>
		<pose>Unspecified</pose>
		<truncated>0</truncated>
		<difficult>0</difficult>
		<bndbox>
			<xmin>2417</xmin>
			<ymin>1041</ymin>
			<xmax>2875</xmax>
			<ymax>1805</ymax>
		</bndbox>
	</object>
	<object>
		<name>.</name>
		<pose>Unspecified</pose>
		<truncated>0</truncated>
		<difficult>0</difficult>
		<bndbox>
			<xmin>2804</xmin>
			<ymin>1073</ymin>
			<xmax>2946</xmax>
			<ymax>1799</ymax>
		</bndbox>
	</object>
	<object>
		<name>8</name>
		<pose>Unspecified</pose>
		<truncated>0</truncated>
		<difficult>0</difficult>
		<bndbox>
			<xmin>2988</xmin>
			<ymin>1044</ymin>
			<xmax>3450</xmax>
			<ymax>1831</ymax>
		</bndbox>
	</object>
</annotation>
